[
  {
    "time": "09:23",
    "timestamp": "25-Mar-2026 09:23 IST",
    "call_oi_chg": 86301,
    "put_oi_chg": 131351,
    "diff": 45050,
    "pcr": 0.83,
    "opt_signal": "BUY",
    "vwap": 26254.75,
    "fut_price": 15666.95,
    "spot_price": 23178.9,
    "vwap_signal": "SELL",
    "nifty_move_pct": 1.16,
    "nearest_level": 23225,
    "nearest_label": "R1",
    "distance_pts": 46.1,
    "rsi_15m": 78.2,
    "ema_signal": "BUY",
    "ema5": 23017.63,
    "ema13": 22954.41,
    "bias": "WATCH BEAR"
  },
  {
    "time": "09:20",
    "timestamp": "25-Mar-2026 09:20 IST",
    "call_oi_chg": 54231,
    "put_oi_chg": 85728,
    "diff": 31497,
    "pcr": 0.85,
    "opt_signal": "BUY",
    "vwap": 23182.7,
    "fut_price": 15670.6,
    "spot_price": 23182.7,
    "vwap_signal": "BUY",
    "nifty_move_pct": 1.18,
    "nearest_level": 23250,
    "nearest_label": "R1",
    "distance_pts": 67.3,
    "rsi_15m": 78.3,
    "ema_signal": "BUY",
    "ema5": 23018.83,
    "ema13": 22954.93,
    "bias": "WATCH BEAR"
  },
  {
    "time": "09:17",
    "timestamp": "25-Mar-2026 09:17 IST",
    "call_oi_chg": 0,
    "put_oi_chg": 0,
    "diff": 0,
    "pcr": 0.85,
    "opt_signal": "NEUTRAL",
    "vwap": 23164.0,
    "fut_price": 15657.8,
    "spot_price": 23164.0,
    "vwap_signal": "BUY",
    "nifty_move_pct": 1.1,
    "nearest_level": null,
    "nearest_label": null,
    "distance_pts": null,
    "rsi_15m": 77.7,
    "ema_signal": "BUY",
    "ema5": 23012.55,
    "ema13": 22952.23,
    "bias": "BEARISH"
  },
  {
    "time": "09:14",
    "timestamp": "25-Mar-2026 09:14 IST",
    "call_oi_chg": 75907,
    "put_oi_chg": 131102,
    "diff": 55195,
    "pcr": 1.2,
    "opt_signal": "BUY",
    "vwap": 25867.07,
    "fut_price": 15424.6,
    "spot_price": 23064.4,
    "vwap_signal": "SELL",
    "nifty_move_pct": 0.66,
    "nearest_level": 23175,
    "nearest_label": "R1",
    "distance_pts": 110.6,
    "rsi_15m": 63.4,
    "ema_signal": "BUY",
    "ema5": 22936.62,
    "ema13": 22916.87,
    "bias": "BEARISH"
  },
  {
    "time": "09:11",
    "timestamp": "25-Mar-2026 09:11 IST",
    "call_oi_chg": 75907,
    "put_oi_chg": 131102,
    "diff": 55195,
    "pcr": 1.2,
    "opt_signal": "BUY",
    "vwap": 25867.07,
    "fut_price": 15424.6,
    "spot_price": 23064.4,
    "vwap_signal": "SELL",
    "nifty_move_pct": 0.66,
    "nearest_level": 23175,
    "nearest_label": "R1",
    "distance_pts": 110.6,
    "rsi_15m": 63.4,
    "ema_signal": "BUY",
    "ema5": 22936.62,
    "ema13": 22916.87,
    "bias": "BEARISH"
  },
  {
    "time": "09:08",
    "timestamp": "25-Mar-2026 09:08 IST",
    "call_oi_chg": 75907,
    "put_oi_chg": 131102,
    "diff": 55195,
    "pcr": 1.2,
    "opt_signal": "BUY",
    "vwap": 25867.07,
    "fut_price": 15424.6,
    "spot_price": 23064.4,
    "vwap_signal": "SELL",
    "nifty_move_pct": 0.66,
    "nearest_level": 23175,
    "nearest_label": "R1",
    "distance_pts": 110.6,
    "rsi_15m": 63.4,
    "ema_signal": "BUY",
    "ema5": 22936.62,
    "ema13": 22916.87,
    "bias": "BEARISH"
  },
  {
    "time": "09:05",
    "timestamp": "25-Mar-2026 09:05 IST",
    "call_oi_chg": 75907,
    "put_oi_chg": 131102,
    "diff": 55195,
    "pcr": 1.2,
    "opt_signal": "BUY",
    "vwap": 25867.07,
    "fut_price": 15424.6,
    "spot_price": 22912.4,
    "vwap_signal": "SELL",
    "nifty_move_pct": 1.78,
    "nearest_level": 23050,
    "nearest_label": "R1",
    "distance_pts": 137.6,
    "rsi_15m": 63.4,
    "ema_signal": "BUY",
    "ema5": 22936.62,
    "ema13": 22916.87,
    "bias": "WATCH BEAR"
  },
  {
    "time": "09:02",
    "timestamp": "25-Mar-2026 09:02 IST",
    "call_oi_chg": 75907,
    "put_oi_chg": 131102,
    "diff": 55195,
    "pcr": 1.2,
    "opt_signal": "BUY",
    "vwap": 25867.07,
    "fut_price": 15424.6,
    "spot_price": 22912.4,
    "vwap_signal": "SELL",
    "nifty_move_pct": 1.78,
    "nearest_level": 23050,
    "nearest_label": "R1",
    "distance_pts": 137.6,
    "rsi_15m": 63.4,
    "ema_signal": "BUY",
    "ema5": 22936.62,
    "ema13": 22916.87,
    "bias": "WATCH BEAR"
  }
]