[
  {
    "time": "12:02",
    "timestamp": "26-Feb-2026 12:02 IST",
    "call_oi_chg": 399112,
    "put_oi_chg": 296571,
    "diff": -102541,
    "pcr": 0.75,
    "opt_signal": "SELL",
    "vwap": 25453.55,
    "fut_price": 16878.0,
    "spot_price": 25453.55,
    "vwap_signal": "BUY",
    "nearest_level": 25450,
    "nearest_label": "S1",
    "distance_pts": 3.5
  },
  {
    "time": "11:59",
    "timestamp": "26-Feb-2026 11:59 IST",
    "call_oi_chg": 397113,
    "put_oi_chg": 309179,
    "diff": -87934,
    "pcr": 0.76,
    "opt_signal": "SELL",
    "vwap": 25457.45,
    "fut_price": 16881.05,
    "spot_price": 25457.45,
    "vwap_signal": "BUY",
    "nearest_level": 25450,
    "nearest_label": "S1",
    "distance_pts": 7.5
  },
  {
    "time": "11:55",
    "timestamp": "26-Feb-2026 11:55 IST",
    "call_oi_chg": 422164,
    "put_oi_chg": 301888,
    "diff": -120276,
    "pcr": 0.68,
    "opt_signal": "SELL",
    "vwap": 25463.15,
    "fut_price": 16888.1,
    "spot_price": 25463.15,
    "vwap_signal": "BUY",
    "nearest_level": 25450,
    "nearest_label": "S1",
    "distance_pts": 13.2
  },
  {
    "time": "11:52",
    "timestamp": "26-Feb-2026 11:52 IST",
    "call_oi_chg": 418244,
    "put_oi_chg": 292329,
    "diff": -125915,
    "pcr": 0.67,
    "opt_signal": "SELL",
    "vwap": 25489.5,
    "fut_price": 16901.35,
    "spot_price": 25489.5,
    "vwap_signal": "BUY",
    "nearest_level": 25450,
    "nearest_label": "S1",
    "distance_pts": 39.5
  },
  {
    "time": "11:49",
    "timestamp": "26-Feb-2026 11:49 IST",
    "call_oi_chg": 372990,
    "put_oi_chg": 291550,
    "diff": -81440,
    "pcr": 0.76,
    "opt_signal": "SELL",
    "vwap": 25482.4,
    "fut_price": 16888.85,
    "spot_price": 25482.4,
    "vwap_signal": "BUY",
    "nearest_level": 25450,
    "nearest_label": "S1",
    "distance_pts": 32.4
  },
  {
    "time": "11:46",
    "timestamp": "26-Feb-2026 11:46 IST",
    "call_oi_chg": 328906,
    "put_oi_chg": 378528,
    "diff": 49622,
    "pcr": 0.86,
    "opt_signal": "BUY",
    "vwap": 25468.95,
    "fut_price": 16879.05,
    "spot_price": 25468.95,
    "vwap_signal": "BUY",
    "nearest_level": 25575,
    "nearest_label": "R1",
    "distance_pts": 106.0
  },
  {
    "time": "11:43",
    "timestamp": "26-Feb-2026 11:43 IST",
    "call_oi_chg": 294757,
    "put_oi_chg": 438399,
    "diff": 143642,
    "pcr": 0.85,
    "opt_signal": "BUY",
    "vwap": 25462.5,
    "fut_price": 16886.65,
    "spot_price": 25462.5,
    "vwap_signal": "BUY",
    "nearest_level": 25575,
    "nearest_label": "R1",
    "distance_pts": 112.5
  },
  {
    "time": "11:40",
    "timestamp": "26-Feb-2026 11:40 IST",
    "call_oi_chg": 259495,
    "put_oi_chg": 476299,
    "diff": 216804,
    "pcr": 0.9,
    "opt_signal": "BUY",
    "vwap": 25496.65,
    "fut_price": 16912.25,
    "spot_price": 25496.65,
    "vwap_signal": "BUY",
    "nearest_level": 25600,
    "nearest_label": "R1",
    "distance_pts": 103.3
  },
  {
    "time": "11:37",
    "timestamp": "26-Feb-2026 11:37 IST",
    "call_oi_chg": 244877,
    "put_oi_chg": 486860,
    "diff": 241983,
    "pcr": 0.92,
    "opt_signal": "BUY",
    "vwap": 25515.6,
    "fut_price": 16921.55,
    "spot_price": 25515.6,
    "vwap_signal": "BUY",
    "nearest_level": 25625,
    "nearest_label": "R1",
    "distance_pts": 109.4
  },
  {
    "time": "11:33",
    "timestamp": "26-Feb-2026 11:33 IST",
    "call_oi_chg": 234187,
    "put_oi_chg": 492051,
    "diff": 257864,
    "pcr": 0.93,
    "opt_signal": "BUY",
    "vwap": 25525.85,
    "fut_price": 16933.45,
    "spot_price": 25525.85,
    "vwap_signal": "BUY",
    "nearest_level": 25625,
    "nearest_label": "R1",
    "distance_pts": 99.2
  },
  {
    "time": "11:31",
    "timestamp": "26-Feb-2026 11:31 IST",
    "call_oi_chg": 248543,
    "put_oi_chg": 453360,
    "diff": 204817,
    "pcr": 0.81,
    "opt_signal": "BUY",
    "vwap": 25530.4,
    "fut_price": 16932.95,
    "spot_price": 25530.4,
    "vwap_signal": "BUY",
    "nearest_level": 25625,
    "nearest_label": "R1",
    "distance_pts": 94.6
  },
  {
    "time": "11:27",
    "timestamp": "26-Feb-2026 11:27 IST",
    "call_oi_chg": 312520,
    "put_oi_chg": 435977,
    "diff": 123457,
    "pcr": 0.76,
    "opt_signal": "BUY",
    "vwap": 25552.25,
    "fut_price": 16954.0,
    "spot_price": 25552.25,
    "vwap_signal": "BUY",
    "nearest_level": 25625,
    "nearest_label": "R1",
    "distance_pts": 72.8
  },
  {
    "time": "11:24",
    "timestamp": "26-Feb-2026 11:24 IST",
    "call_oi_chg": 335503,
    "put_oi_chg": 425448,
    "diff": 89945,
    "pcr": 0.74,
    "opt_signal": "BUY",
    "vwap": 25538.05,
    "fut_price": 16944.25,
    "spot_price": 25538.05,
    "vwap_signal": "BUY",
    "nearest_level": 25625,
    "nearest_label": "R1",
    "distance_pts": 87.0
  },
  {
    "time": "11:21",
    "timestamp": "26-Feb-2026 11:21 IST",
    "call_oi_chg": 339908,
    "put_oi_chg": 412418,
    "diff": 72510,
    "pcr": 0.72,
    "opt_signal": "BUY",
    "vwap": 25526.8,
    "fut_price": 16941.65,
    "spot_price": 25526.8,
    "vwap_signal": "BUY",
    "nearest_level": 25625,
    "nearest_label": "R1",
    "distance_pts": 98.2
  },
  {
    "time": "11:18",
    "timestamp": "26-Feb-2026 11:18 IST",
    "call_oi_chg": 352636,
    "put_oi_chg": 424503,
    "diff": 71867,
    "pcr": 0.8,
    "opt_signal": "BUY",
    "vwap": 25533.15,
    "fut_price": 16945.9,
    "spot_price": 25533.15,
    "vwap_signal": "BUY",
    "nearest_level": 25625,
    "nearest_label": "R1",
    "distance_pts": 91.8
  },
  {
    "time": "11:15",
    "timestamp": "26-Feb-2026 11:15 IST",
    "call_oi_chg": 349748,
    "put_oi_chg": 424000,
    "diff": 74252,
    "pcr": 0.8,
    "opt_signal": "BUY",
    "vwap": 25524.3,
    "fut_price": 16945.2,
    "spot_price": 25524.3,
    "vwap_signal": "BUY",
    "nearest_level": 25625,
    "nearest_label": "R1",
    "distance_pts": 100.7
  },
  {
    "time": "11:12",
    "timestamp": "26-Feb-2026 11:12 IST",
    "call_oi_chg": 347354,
    "put_oi_chg": 420759,
    "diff": 73405,
    "pcr": 0.8,
    "opt_signal": "BUY",
    "vwap": 25523.3,
    "fut_price": 16946.95,
    "spot_price": 25523.3,
    "vwap_signal": "BUY",
    "nearest_level": 25625,
    "nearest_label": "R1",
    "distance_pts": 101.7
  },
  {
    "time": "11:08",
    "timestamp": "26-Feb-2026 11:08 IST",
    "call_oi_chg": 345904,
    "put_oi_chg": 410385,
    "diff": 64481,
    "pcr": 0.79,
    "opt_signal": "BUY",
    "vwap": 25514.7,
    "fut_price": 16936.95,
    "spot_price": 25514.7,
    "vwap_signal": "BUY",
    "nearest_level": 25625,
    "nearest_label": "R1",
    "distance_pts": 110.3
  },
  {
    "time": "11:05",
    "timestamp": "26-Feb-2026 11:05 IST",
    "call_oi_chg": 346271,
    "put_oi_chg": 390137,
    "diff": 43866,
    "pcr": 0.78,
    "opt_signal": "BUY",
    "vwap": 25515.9,
    "fut_price": 16930.6,
    "spot_price": 25515.9,
    "vwap_signal": "BUY",
    "nearest_level": 25625,
    "nearest_label": "R1",
    "distance_pts": 109.1
  },
  {
    "time": "11:04",
    "timestamp": "26-Feb-2026 11:04 IST",
    "call_oi_chg": 330106,
    "put_oi_chg": 413259,
    "diff": 83153,
    "pcr": 0.81,
    "opt_signal": "BUY",
    "vwap": 25517.85,
    "fut_price": 16936.8,
    "spot_price": 25517.85,
    "vwap_signal": "BUY",
    "nearest_level": 25625,
    "nearest_label": "R1",
    "distance_pts": 107.2
  },
  {
    "time": "11:02",
    "timestamp": "26-Feb-2026 11:02 IST",
    "call_oi_chg": 314279,
    "put_oi_chg": 430141,
    "diff": 115862,
    "pcr": 0.83,
    "opt_signal": "BUY",
    "vwap": 25502.3,
    "fut_price": 16922.35,
    "spot_price": 25502.3,
    "vwap_signal": "BUY",
    "nearest_level": 25600,
    "nearest_label": "R1",
    "distance_pts": 97.7
  },
  {
    "time": "11:00",
    "timestamp": "26-Feb-2026 11:00 IST",
    "call_oi_chg": 314279,
    "put_oi_chg": 430141,
    "diff": 115862,
    "pcr": 0.83,
    "opt_signal": "BUY",
    "vwap": 25498.85,
    "fut_price": 16925.15,
    "spot_price": 25498.85,
    "vwap_signal": "BUY",
    "nearest_level": 25600,
    "nearest_label": "R1",
    "distance_pts": 101.2
  },
  {
    "time": "10:59",
    "timestamp": "26-Feb-2026 10:59 IST",
    "call_oi_chg": 314246,
    "put_oi_chg": 430196,
    "diff": 115950,
    "pcr": 0.83,
    "opt_signal": "BUY",
    "vwap": 25509.6,
    "fut_price": 16929.0,
    "spot_price": 25509.6,
    "vwap_signal": "BUY",
    "nearest_level": 25625,
    "nearest_label": "R1",
    "distance_pts": 115.4
  },
  {
    "time": "10:56",
    "timestamp": "26-Feb-2026 10:56 IST",
    "call_oi_chg": 297328,
    "put_oi_chg": 419385,
    "diff": 122057,
    "pcr": 0.75,
    "opt_signal": "BUY",
    "vwap": 25513.85,
    "fut_price": 16931.2,
    "spot_price": 25513.85,
    "vwap_signal": "BUY",
    "nearest_level": 25625,
    "nearest_label": "R1",
    "distance_pts": 111.2
  },
  {
    "time": "10:53",
    "timestamp": "26-Feb-2026 10:53 IST",
    "call_oi_chg": 293437,
    "put_oi_chg": 414665,
    "diff": 121228,
    "pcr": 0.75,
    "opt_signal": "BUY",
    "vwap": 25530.9,
    "fut_price": 16953.2,
    "spot_price": 25530.9,
    "vwap_signal": "BUY",
    "nearest_level": 25625,
    "nearest_label": "R1",
    "distance_pts": 94.1
  },
  {
    "time": "10:50",
    "timestamp": "26-Feb-2026 10:50 IST",
    "call_oi_chg": 295114,
    "put_oi_chg": 401342,
    "diff": 106228,
    "pcr": 0.74,
    "opt_signal": "BUY",
    "vwap": 25545.95,
    "fut_price": 16959.35,
    "spot_price": 25545.95,
    "vwap_signal": "BUY",
    "nearest_level": 25625,
    "nearest_label": "R1",
    "distance_pts": 79.0
  },
  {
    "time": "10:49",
    "timestamp": "26-Feb-2026 10:49 IST",
    "call_oi_chg": 295114,
    "put_oi_chg": 401342,
    "diff": 106228,
    "pcr": 0.74,
    "opt_signal": "BUY",
    "vwap": 25550.25,
    "fut_price": 16959.5,
    "spot_price": 25550.25,
    "vwap_signal": "BUY",
    "nearest_level": 25625,
    "nearest_label": "R1",
    "distance_pts": 74.8
  },
  {
    "time": "10:47",
    "timestamp": "26-Feb-2026 10:47 IST",
    "call_oi_chg": 289504,
    "put_oi_chg": 390372,
    "diff": 100868,
    "pcr": 0.74,
    "opt_signal": "BUY",
    "vwap": 25531.75,
    "fut_price": 16955.85,
    "spot_price": 25531.75,
    "vwap_signal": "BUY",
    "nearest_level": 25625,
    "nearest_label": "R1",
    "distance_pts": 93.2
  },
  {
    "time": "10:46",
    "timestamp": "26-Feb-2026 10:46 IST",
    "call_oi_chg": 289502,
    "put_oi_chg": 390372,
    "diff": 100870,
    "pcr": 0.74,
    "opt_signal": "BUY",
    "vwap": 25531.45,
    "fut_price": 16956.35,
    "spot_price": 25531.45,
    "vwap_signal": "BUY",
    "nearest_level": 25625,
    "nearest_label": "R1",
    "distance_pts": 93.5
  },
  {
    "time": "10:43",
    "timestamp": "26-Feb-2026 10:43 IST",
    "call_oi_chg": 285342,
    "put_oi_chg": 399990,
    "diff": 114648,
    "pcr": 0.75,
    "opt_signal": "BUY",
    "vwap": 25532.35,
    "fut_price": 16957.1,
    "spot_price": 25532.35,
    "vwap_signal": "BUY",
    "nearest_level": 25625,
    "nearest_label": "R1",
    "distance_pts": 92.7
  },
  {
    "time": "10:37",
    "timestamp": "26-Feb-2026 10:37 IST",
    "call_oi_chg": 266098,
    "put_oi_chg": 395445,
    "diff": 129347,
    "pcr": 0.75,
    "opt_signal": "BUY",
    "vwap": 25531.25,
    "fut_price": 16955.85,
    "spot_price": 25531.25,
    "vwap_signal": "BUY"
  },
  {
    "time": "10:34",
    "timestamp": "26-Feb-2026 10:34 IST",
    "call_oi_chg": 261647,
    "put_oi_chg": 402494,
    "diff": 140847,
    "pcr": 0.76,
    "opt_signal": "BUY",
    "vwap": 25536.4,
    "fut_price": 16946.7,
    "spot_price": 25536.4,
    "vwap_signal": "BUY"
  },
  {
    "time": "10:31",
    "timestamp": "26-Feb-2026 10:31 IST",
    "call_oi_chg": 264520,
    "put_oi_chg": 427803,
    "diff": 163283,
    "pcr": 0.78,
    "opt_signal": "BUY",
    "vwap": 25525.25,
    "fut_price": 16942.5,
    "spot_price": 25525.25,
    "vwap_signal": "BUY"
  },
  {
    "time": "10:28",
    "timestamp": "26-Feb-2026 10:28 IST",
    "call_oi_chg": 246592,
    "put_oi_chg": 441780,
    "diff": 195188,
    "pcr": 0.8,
    "opt_signal": "BUY",
    "vwap": 25540.95,
    "fut_price": 16954.85,
    "spot_price": 25540.95,
    "vwap_signal": "BUY"
  },
  {
    "time": "10:25",
    "timestamp": "26-Feb-2026 10:25 IST",
    "call_oi_chg": 237360,
    "put_oi_chg": 446921,
    "diff": 209561,
    "pcr": 0.81,
    "opt_signal": "BUY",
    "vwap": 25537.65,
    "fut_price": 16945.85,
    "spot_price": 25537.65,
    "vwap_signal": "BUY"
  },
  {
    "time": "10:23",
    "timestamp": "26-Feb-2026 10:23 IST",
    "call_oi_chg": 237360,
    "put_oi_chg": 446921,
    "diff": 209561,
    "pcr": 0.81,
    "opt_signal": "BUY",
    "vwap": 25537.05,
    "fut_price": 16945.0,
    "spot_price": 25537.05,
    "vwap_signal": "BUY"
  },
  {
    "time": "10:22",
    "timestamp": "26-Feb-2026 10:22 IST",
    "call_oi_chg": 235057,
    "put_oi_chg": 439413,
    "diff": 204356,
    "pcr": 0.81,
    "opt_signal": "BUY",
    "vwap": 25545.5,
    "fut_price": 16941.6,
    "spot_price": 25545.5,
    "vwap_signal": "BUY"
  },
  {
    "time": "10:19",
    "timestamp": "26-Feb-2026 10:19 IST",
    "call_oi_chg": 226530,
    "put_oi_chg": 437729,
    "diff": 211199,
    "pcr": 0.81,
    "opt_signal": "BUY",
    "vwap": 25558.9,
    "fut_price": 16939.45,
    "spot_price": 25558.9,
    "vwap_signal": "BUY"
  },
  {
    "time": "10:18",
    "timestamp": "26-Feb-2026 10:18 IST",
    "call_oi_chg": 226530,
    "put_oi_chg": 437729,
    "diff": 211199,
    "pcr": 0.81,
    "opt_signal": "BUY",
    "vwap": 25554.85,
    "fut_price": 16940.2,
    "spot_price": 25554.85,
    "vwap_signal": "BUY"
  },
  {
    "time": "10:15",
    "timestamp": "26-Feb-2026 10:15 IST",
    "call_oi_chg": 228295,
    "put_oi_chg": 438636,
    "diff": 210341,
    "pcr": 0.89,
    "opt_signal": "BUY",
    "vwap": 25553.75,
    "fut_price": 16945.0,
    "spot_price": 25553.75,
    "vwap_signal": "BUY"
  },
  {
    "time": "10:14",
    "timestamp": "26-Feb-2026 10:14 IST",
    "call_oi_chg": 253886,
    "put_oi_chg": 426011,
    "diff": 172125,
    "pcr": 0.86,
    "opt_signal": "BUY",
    "vwap": 25561.4,
    "fut_price": 16950.1,
    "spot_price": 25561.4,
    "vwap_signal": "BUY"
  },
  {
    "time": "10:12",
    "timestamp": "26-Feb-2026 10:12 IST",
    "call_oi_chg": 253886,
    "put_oi_chg": 426011,
    "diff": 172125,
    "pcr": 0.86,
    "opt_signal": "BUY",
    "vwap": 25559.65,
    "fut_price": 16954.0,
    "spot_price": 25559.65,
    "vwap_signal": "BUY"
  },
  {
    "time": "10:09",
    "timestamp": "26-Feb-2026 10:09 IST",
    "call_oi_chg": 291322,
    "put_oi_chg": 378266,
    "diff": 86944,
    "pcr": 0.8,
    "opt_signal": "BUY",
    "vwap": 25553.6,
    "fut_price": 16955.4,
    "spot_price": 25553.6,
    "vwap_signal": "BUY"
  },
  {
    "time": "10:06",
    "timestamp": "26-Feb-2026 10:06 IST",
    "call_oi_chg": 322742,
    "put_oi_chg": 361768,
    "diff": 39026,
    "pcr": 0.77,
    "opt_signal": "BUY",
    "vwap": 25552.3,
    "fut_price": 16947.85,
    "spot_price": 25552.3,
    "vwap_signal": "BUY"
  },
  {
    "time": "10:03",
    "timestamp": "26-Feb-2026 10:03 IST",
    "call_oi_chg": 325745,
    "put_oi_chg": 365335,
    "diff": 39590,
    "pcr": 0.77,
    "opt_signal": "BUY",
    "vwap": 25532.9,
    "fut_price": 16937.45,
    "spot_price": 25532.9,
    "vwap_signal": "BUY"
  },
  {
    "time": "10:00",
    "timestamp": "26-Feb-2026 10:00 IST",
    "call_oi_chg": 307574,
    "put_oi_chg": 361604,
    "diff": 54030,
    "pcr": 0.78,
    "opt_signal": "BUY",
    "vwap": 25522.25,
    "fut_price": 16945.25,
    "spot_price": 25522.25,
    "vwap_signal": "BUY"
  },
  {
    "time": "09:57",
    "timestamp": "26-Feb-2026 09:57 IST",
    "call_oi_chg": 265158,
    "put_oi_chg": 378922,
    "diff": 113764,
    "pcr": 0.82,
    "opt_signal": "BUY",
    "vwap": 25513.55,
    "fut_price": 16946.3,
    "spot_price": 25513.55,
    "vwap_signal": "BUY"
  },
  {
    "time": "09:54",
    "timestamp": "26-Feb-2026 09:54 IST",
    "call_oi_chg": 268898,
    "put_oi_chg": 391732,
    "diff": 122834,
    "pcr": 0.75,
    "opt_signal": "BUY",
    "vwap": 25530.35,
    "fut_price": 16947.9,
    "spot_price": 25530.35,
    "vwap_signal": "BUY"
  },
  {
    "time": "09:53",
    "timestamp": "26-Feb-2026 09:53 IST",
    "call_oi_chg": 270319,
    "put_oi_chg": 368366,
    "diff": 98047,
    "pcr": 0.73,
    "opt_signal": "BUY",
    "vwap": 25545.3,
    "fut_price": 16957.3,
    "spot_price": 25545.3,
    "vwap_signal": "BUY"
  },
  {
    "time": "09:32",
    "timestamp": "26-Feb-2026 09:32 IST",
    "call_oi_chg": 266170,
    "put_oi_chg": 241510,
    "diff": -24660,
    "pcr": 0.71,
    "opt_signal": "SELL",
    "vwap": 25500.5,
    "fut_price": 16857.4,
    "spot_price": 25500.5,
    "vwap_signal": "BUY"
  },
  {
    "time": "09:29",
    "timestamp": "26-Feb-2026 09:29 IST",
    "call_oi_chg": 266170,
    "put_oi_chg": 241510,
    "diff": -24660,
    "pcr": 0.71,
    "opt_signal": "SELL",
    "vwap": 25507.1,
    "fut_price": 16859.75,
    "spot_price": 25507.1,
    "vwap_signal": "BUY"
  },
  {
    "time": "09:25",
    "timestamp": "26-Feb-2026 09:25 IST",
    "call_oi_chg": 237951,
    "put_oi_chg": 194867,
    "diff": -43084,
    "pcr": 0.69,
    "opt_signal": "SELL",
    "vwap": 25491.6,
    "fut_price": 16847.1,
    "spot_price": 25491.6,
    "vwap_signal": "BUY"
  },
  {
    "time": "09:22",
    "timestamp": "26-Feb-2026 09:22 IST",
    "call_oi_chg": 137887,
    "put_oi_chg": 83868,
    "diff": -54019,
    "pcr": 0.57,
    "opt_signal": "SELL",
    "vwap": 25495.45,
    "fut_price": 16853.65,
    "spot_price": 25495.45,
    "vwap_signal": "BUY"
  },
  {
    "time": "09:19",
    "timestamp": "26-Feb-2026 09:19 IST",
    "call_oi_chg": 31177,
    "put_oi_chg": 30720,
    "diff": -457,
    "pcr": 0.57,
    "opt_signal": "SELL",
    "vwap": 25538.95,
    "fut_price": 16887.0,
    "spot_price": 25538.95,
    "vwap_signal": "BUY"
  },
  {
    "time": "09:16",
    "timestamp": "26-Feb-2026 09:16 IST",
    "call_oi_chg": 0,
    "put_oi_chg": 0,
    "diff": 0,
    "pcr": 0.56,
    "opt_signal": "NEUTRAL",
    "vwap": 25543.25,
    "fut_price": 16881.1,
    "spot_price": 25543.25,
    "vwap_signal": "BUY"
  },
  {
    "time": "02:20",
    "timestamp": "26-Feb-2026 02:20 IST",
    "call_oi_chg": 354860,
    "put_oi_chg": 263012,
    "diff": -91848,
    "pcr": 0.66,
    "opt_signal": "SELL",
    "vwap": 25482.5,
    "fut_price": 16825.6,
    "spot_price": 25482.5,
    "vwap_signal": "BUY"
  },
  {
    "time": "02:13",
    "timestamp": "26-Feb-2026 02:13 IST",
    "call_oi_chg": 354860,
    "put_oi_chg": 263012,
    "diff": -91848,
    "pcr": 0.66,
    "opt_signal": "SELL",
    "vwap": 25482.5,
    "fut_price": 16825.6,
    "spot_price": 25482.5,
    "vwap_signal": "BUY"
  },
  {
    "time": "02:04",
    "timestamp": "26-Feb-2026 02:04 IST",
    "call_oi_chg": 354860,
    "put_oi_chg": 263012,
    "diff": -91848,
    "pcr": 0.66,
    "opt_signal": "SELL",
    "vwap": 25482.5,
    "fut_price": 16825.6,
    "spot_price": 25482.5,
    "vwap_signal": "BUY"
  },
  {
    "time": "01:51",
    "timestamp": "26-Feb-2026 01:51 IST",
    "call_oi_chg": 354860,
    "put_oi_chg": 263012,
    "diff": -91848,
    "pcr": 0.66,
    "opt_signal": "SELL",
    "vwap": 25482.5,
    "fut_price": 16825.6,
    "spot_price": 25482.5,
    "vwap_signal": "BUY"
  },
  {
    "time": "01:49",
    "timestamp": "26-Feb-2026 01:49 IST",
    "call_oi_chg": 354860,
    "put_oi_chg": 263012,
    "diff": -91848,
    "pcr": 0.66,
    "opt_signal": "SELL",
    "vwap": 25482.5,
    "fut_price": 16825.6,
    "spot_price": 25482.5,
    "vwap_signal": "BUY"
  },
  {
    "time": "01:40",
    "timestamp": "26-Feb-2026 01:40 IST",
    "call_oi_chg": 354860,
    "put_oi_chg": 263012,
    "diff": -91848,
    "pcr": 0.66,
    "opt_signal": "SELL",
    "vwap": 25482.5,
    "fut_price": 16825.6,
    "spot_price": 25482.5,
    "vwap_signal": "BUY"
  },
  {
    "time": "01:34",
    "timestamp": "26-Feb-2026 01:34 IST",
    "call_oi_chg": 354860,
    "put_oi_chg": 263012,
    "diff": -91848,
    "pcr": 0.66,
    "opt_signal": "SELL",
    "vwap": 25482.5,
    "fut_price": 16825.6,
    "spot_price": 25482.5,
    "vwap_signal": "BUY"
  },
  {
    "time": "01:16",
    "timestamp": "26-Feb-2026 01:16 IST",
    "call_oi_chg": 354860,
    "put_oi_chg": 263012,
    "diff": -91848,
    "pcr": 0.66,
    "opt_signal": "SELL",
    "vwap": 25482.5,
    "fut_price": 16825.6,
    "spot_price": 25482.5,
    "vwap_signal": "BUY"
  }
]